serapis_metrics/__init__.py
serapis_metrics/core.py
serapis_metrics-1.0.1.dist-info/licenses/LICENSE.md
serapis_metrics-1.0.1.dist-info/METADATA
serapis_metrics-1.0.1.dist-info/WHEEL
serapis_metrics-1.0.1.dist-info/top_level.txt
serapis_metrics-1.0.1.dist-info/RECORD
