Metadata-Version: 2.4
Name: serapis-metrics
Version: 1.0.1
Summary: A metrics collection library for Serapis projects with multi-Python support
Home-page: https://github.com/adtTEyS/Serapis-Metrics
Author: Serapis Team
Author-email: rcebrian@typsa.es
Project-URL: Bug Reports, https://github.com/adtTEyS/Serapis-Metrics/issues
Project-URL: Source, https://github.com/adtTEyS/Serapis-Metrics
Keywords: metrics,pyrevit,revit,serapis
Classifier: Development Status :: 4 - Beta
Classifier: Intended Audience :: Developers
Classifier: License :: OSI Approved :: MIT License
Classifier: Operating System :: OS Independent
Classifier: Programming Language :: Python :: 2.7
Classifier: Programming Language :: Python :: 3
Classifier: Programming Language :: Python :: 3.7
Classifier: Programming Language :: Python :: 3.8
Classifier: Programming Language :: Python :: 3.9
Classifier: Programming Language :: Python :: 3.10
Classifier: Programming Language :: Python :: 3.11
Classifier: Programming Language :: Python :: Implementation :: IronPython
Classifier: Topic :: Software Development :: Libraries :: Python Modules
Requires-Python: >=2.7
License-File: LICENSE.md
Dynamic: author
Dynamic: author-email
Dynamic: classifier
Dynamic: description
Dynamic: description-content-type
Dynamic: home-page
Dynamic: keywords
Dynamic: license-file
Dynamic: project-url
Dynamic: requires-python
Dynamic: summary
